qoai_cirq/__init__.py
qoai_cirq-0.0.1.dist-info/LICENCE.txt
qoai_cirq-0.0.1.dist-info/METADATA
qoai_cirq-0.0.1.dist-info/WHEEL
qoai_cirq-0.0.1.dist-info/top_level.txt
qoai_cirq-0.0.1.dist-info/RECORD
