Metadata-Version: 2.1
Name: qoai-cirq
Version: 0.0.1
Summary: Cirq Quantum API and Access Provider
Author: QuantumOpenAI
Author-email: team@quantumopenai.com
Classifier: Programming Language :: Python :: 3
Classifier: License :: OSI Approved :: MIT License
Classifier: Operating System :: OS Independent
License-File: LICENCE.txt
Requires-Dist: cirq
